fusions/__init__.py
fusions/cfm.py
fusions/diffusion.py
fusions/integrate.py
fusions/model.py
fusions/network.py
fusions/optimal_transport.py
fusions/plotting.py
fusions/utils.py
fusions-0.4.3.dist-info/LICENSE
fusions-0.4.3.dist-info/METADATA
fusions-0.4.3.dist-info/WHEEL
fusions-0.4.3.dist-info/RECORD
