Metadata-Version: 2.1
Name: fusions
Version: 0.4.3
Summary: Diffusion meets sampling
Author: David Yallup
Author-email: david.yallup@gmail.com
Requires-Python: >=3.9,<4.0
Classifier: Programming Language :: Python :: 3
Classifier: Programming Language :: Python :: 3.9
Classifier: Programming Language :: Python :: 3.10
Classifier: Programming Language :: Python :: 3.11
Classifier: Programming Language :: Python :: 3.12
Requires-Dist: anesthetic (>=2.4.2,<3.0.0)
Requires-Dist: diffrax (>=0.4.0,<0.5.0)
Requires-Dist: distrax (>=0.1.5,<0.2.0)
Requires-Dist: flax (>=0.8.2,<0.9.0)
Requires-Dist: optax (>=0.2.2,<0.3.0)
Requires-Dist: pytest (>=7.3,<8.0)
Requires-Dist: torch (>=2.1.0,<3.0.0)
Requires-Dist: tqdm (>=4.62.0,<5.0.0)
